{
  "results": [
    {
      "test": "/wai-aria/alertdialog_modal_false-manual.html",
      "subtests": [
        {
          "name": "alertdialog modal false",
          "status": "PASS",
          "message": null
        },
        {
          "name": "alertdialog modal false 1",
          "status": "FAIL",
          "message": "assert_false: NOTRUN: No assertion for API IAccessible2 expected false got true"
        }
      ],
      "status": "OK",
      "message": null
    },
    {
      "test": "/wai-aria/alertdialog_modal_true-manual.html",
      "subtests": [
        {
          "name": "alertdialog modal true",
          "status": "PASS",
          "message": null
        },
        {
          "name": "alertdialog modal true 1",
          "status": "FAIL",
          "message": "assert_false: NOTRUN: No assertion for API IAccessible2 expected false got true"
        }
      ],
      "status": "OK",
      "message": null
    },
    {
      "test": "/wai-aria/application_activedescendant-manual.html",
      "subtests": [],
      "status": "NOTRUN",
      "message": "No steps for AT API IAccessible2"
    },
    {
      "test": "/wai-aria/application_activedescendant_value_changes-manual.html",
      "subtests": [
        {
          "name": "application activedescendant value changes",
          "status": "PASS",
          "message": null
        },
        {
          "name": "application activedescendant value changes 1",
          "status": "FAIL",
          "message": "assert_false: NOTRUN: No assertion for API IAccessible2 expected false got true"
        }
      ],
      "status": "OK",
      "message": null
    },
    {
      "test": "/wai-aria/aria-current_not_declared-manual.html",
      "subtests": [
        {
          "name": "aria-current not declared",
          "status": "PASS",
          "message": null
        }
      ],
      "status": "OK",
      "message": null
    },
    {
      "test": "/wai-aria/aria-current_with_value_changes-manual.html",
      "subtests": [
        {
          "name": "aria-current with value changes",
          "status": "FAIL",
          "message": "assert_true: \"property objectAttributes contains current:false\" failed ; \"event type is IA2_EVENT_OBJECT_ATTRIBUTE_CHANGED\" failed ;  expected true got false"
        }
      ],
      "status": "OK",
      "message": null
    },
    {
      "test": "/wai-aria/aria-current_with_value_date-manual.html",
      "subtests": [
        {
          "name": "aria-current with value date",
          "status": "PASS",
          "message": null
        }
      ],
      "status": "OK",
      "message": null
    },
    {
      "test": "/wai-aria/aria-current_with_value_location-manual.html",
      "subtests": [
        {
          "name": "aria-current with value location",
          "status": "FAIL",
          "message": "assert_true: \"property interfaces contains IAccessibleImage\" failed ;  expected true got false"
        }
      ],
      "status": "OK",
      "message": null
    },
    {
      "test": "/wai-aria/aria-current_with_value_page-manual.html",
      "subtests": [
        {
          "name": "aria-current with value page",
          "status": "FAIL",
          "message": "assert_true: \"property interfaces contains IAccessibleHypertext\" failed ;  expected true got false"
        }
      ],
      "status": "OK",
      "message": null
    },
    {
      "test": "/wai-aria/aria-current_with_value_step-manual.html",
      "subtests": [
        {
          "name": "aria-current with value step",
          "status": "FAIL",
          "message": "assert_true: \"property interfaces contains IAccessibleHypertext\" failed ;  expected true got false"
        }
      ],
      "status": "OK",
      "message": null
    },
    {
      "test": "/wai-aria/aria-current_with_value_time-manual.html",
      "subtests": [
        {
          "name": "aria-current with value time",
          "status": "PASS",
          "message": null
        }
      ],
      "status": "OK",
      "message": null
    },
    {
      "test": "/wai-aria/aria-current_with_value_true-manual.html",
      "subtests": [
        {
          "name": "aria-current with value true",
          "status": "PASS",
          "message": null
        }
      ],
      "status": "OK",
      "message": null
    },
    {
      "test": "/wai-aria/aria-current_with_value_unspecified-manual.html",
      "subtests": [
        {
          "name": "aria-current with value unspecified",
          "status": "PASS",
          "message": null
        }
      ],
      "status": "OK",
      "message": null
    },
    {
      "test": "/wai-aria/aria-details_pointing_to_details_element-manual.html",
      "subtests": [
        {
          "name": "aria-details pointing to details element",
          "status": "PASS",
          "message": null
        },
        {
          "name": "aria-details pointing to details element 1",
          "status": "PASS",
          "message": null
        }
      ],
      "status": "OK",
      "message": null
    },
    {
      "test": "/wai-aria/aria-details_pointing_to_div_element-manual.html",
      "subtests": [
        {
          "name": "aria-details pointing to div element",
          "status": "PASS",
          "message": null
        },
        {
          "name": "aria-details pointing to div element 1",
          "status": "PASS",
          "message": null
        }
      ],
      "status": "OK",
      "message": null
    },
    {
      "test": "/wai-aria/article_in_feed_posinset_and_setsize-manual.html",
      "subtests": [
        {
          "name": "article in feed posinset and setsize",
          "status": "PASS",
          "message": null
        }
      ],
      "status": "OK",
      "message": null
    },
    {
      "test": "/wai-aria/article_in_feed_setsize_-1-manual.html",
      "subtests": [
        {
          "name": "article in feed setsize -1",
          "status": "FAIL",
          "message": "assert_true: \"property objectAttributes contains setsize:-1\" failed ; \"property groupPosition contains similarItemsInGroup:-1\" failed ;  expected true got false"
        }
      ],
      "status": "OK",
      "message": null
    },
    {
      "test": "/wai-aria/article_not_in_feed_posinset_and_setsize-manual.html",
      "subtests": [
        {
          "name": "article not in feed posinset and setsize",
          "status": "PASS",
          "message": null
        }
      ],
      "status": "OK",
      "message": null
    },
    {
      "test": "/wai-aria/button_haspopup_dialog-manual.html",
      "subtests": [
        {
          "name": "button haspopup dialog",
          "status": "PASS",
          "message": null
        }
      ],
      "status": "OK",
      "message": null
    },
    {
      "test": "/wai-aria/button_haspopup_emptystring-manual.html",
      "subtests": [
        {
          "name": "button haspopup emptystring",
          "status": "FAIL",
          "message": "assert_true: \"property objectAttributes contains haspopup:false\" failed ;  expected true got false"
        }
      ],
      "status": "OK",
      "message": null
    },
    {
      "test": "/wai-aria/button_haspopup_false-manual.html",
      "subtests": [
        {
          "name": "button haspopup false",
          "status": "FAIL",
          "message": "assert_true: \"property objectAttributes contains haspopup:false\" failed ;  expected true got false"
        }
      ],
      "status": "OK",
      "message": null
    },
    {
      "test": "/wai-aria/button_haspopup_foo-manual.html",
      "subtests": [
        {
          "name": "button haspopup foo",
          "status": "FAIL",
          "message": "assert_true: \"property objectAttributes contains haspopup:false\" failed ;  expected true got false"
        }
      ],
      "status": "OK",
      "message": null
    },
    {
      "test": "/wai-aria/button_haspopup_grid-manual.html",
      "subtests": [
        {
          "name": "button haspopup grid",
          "status": "PASS",
          "message": null
        }
      ],
      "status": "OK",
      "message": null
    },
    {
      "test": "/wai-aria/button_haspopup_listbox-manual.html",
      "subtests": [
        {
          "name": "button haspopup listbox",
          "status": "PASS",
          "message": null
        }
      ],
      "status": "OK",
      "message": null
    },
    {
      "test": "/wai-aria/button_haspopup_menu-manual.html",
      "subtests": [
        {
          "name": "button haspopup menu",
          "status": "PASS",
          "message": null
        }
      ],
      "status": "OK",
      "message": null
    },
    {
      "test": "/wai-aria/button_haspopup_tree-manual.html",
      "subtests": [
        {
          "name": "button haspopup tree",
          "status": "PASS",
          "message": null
        }
      ],
      "status": "OK",
      "message": null
    },
    {
      "test": "/wai-aria/button_haspopup_true-manual.html",
      "subtests": [
        {
          "name": "button haspopup true",
          "status": "FAIL",
          "message": "assert_true: \"property role is ROLE_SYSTEM_PUSHBUTTON\" failed ; \"property objectAttributes contains haspopup:menu\" failed ;  expected true got false"
        }
      ],
      "status": "OK",
      "message": null
    },
    {
      "test": "/wai-aria/button_haspopup_unspecified-manual.html",
      "subtests": [
        {
          "name": "button haspopup unspecified",
          "status": "FAIL",
          "message": "assert_true: \"property objectAttributes contains haspopup:false\" failed ;  expected true got false"
        }
      ],
      "status": "OK",
      "message": null
    },
    {
      "test": "/wai-aria/button_roledescription_empty-manual.html",
      "subtests": [
        {
          "name": "button roledescription empty",
          "status": "FAIL",
          "message": "assert_true: \"property localizedExtendedRole is null\" failed ;  expected true got false"
        }
      ],
      "status": "OK",
      "message": null
    },
    {
      "test": "/wai-aria/button_roledescription_valid-manual.html",
      "subtests": [
        {
          "name": "button roledescription valid",
          "status": "FAIL",
          "message": "assert_true: \"property localizedExtendedRole is SassyButton\" failed ;  expected true got false"
        }
      ],
      "status": "OK",
      "message": null
    },
    {
      "test": "/wai-aria/button_roledescription_whitespace_only-manual.html",
      "subtests": [
        {
          "name": "button roledescription whitespace only",
          "status": "FAIL",
          "message": "assert_true: \"property localizedExtendedRole is null\" failed ;  expected true got false"
        }
      ],
      "status": "OK",
      "message": null
    },
    {
      "test": "/wai-aria/cell-manual.html",
      "subtests": [
        {
          "name": "cell",
          "status": "FAIL",
          "message": "assert_false: NOTRUN: No assertion for API IAccessible2 expected false got true"
        },
        {
          "name": "cell 1",
          "status": "FAIL",
          "message": "assert_true: \"property objectAttributes contains colcount:8\" failed ;  expected true got false"
        }
      ],
      "status": "OK",
      "message": null
    },
    {
      "test": "/wai-aria/cell_aria-colspan_2_on_div-manual.html",
      "subtests": [
        {
          "name": "cell aria-colspan 2 on div",
          "status": "PASS",
          "message": null
        }
      ],
      "status": "OK",
      "message": null
    },
    {
      "test": "/wai-aria/cell_aria-colspan_2_on_td_html_colspan_3-manual.html",
      "subtests": [
        {
          "name": "cell aria-colspan 2 on td html colspan 3",
          "status": "FAIL",
          "message": "assert_true: \"property objectAttributes doesNotContain colspan:2\" failed ;  expected true got false"
        }
      ],
      "status": "OK",
      "message": null
    },
    {
      "test": "/wai-aria/cell_aria-colspan_2_on_td_html_colspan_3_with_headers_and_border-manual.html",
      "subtests": [
        {
          "name": "cell aria-colspan 2 on td html colspan 3 with headers and border",
          "status": "FAIL",
          "message": "assert_true: \"property objectAttributes doesNotContain colspan:2\" failed ;  expected true got false"
        }
      ],
      "status": "OK",
      "message": null
    },
    {
      "test": "/wai-aria/cell_aria-colspan_2_on_td_html_colspan_3_with_three_actual_columns-manual.html",
      "subtests": [
        {
          "name": "cell aria-colspan 2 on td html colspan 3 with three actual columns",
          "status": "FAIL",
          "message": "assert_true: \"property objectAttributes doesNotContain colspan:2\" failed ;  expected true got false"
        }
      ],
      "status": "OK",
      "message": null
    },
    {
      "test": "/wai-aria/cell_aria-colspan_2_on_td_with_html_colspan_not_specified-manual.html",
      "subtests": [
        {
          "name": "cell aria-colspan 2 on td with html colspan not specified",
          "status": "PASS",
          "message": null
        }
      ],
      "status": "OK",
      "message": null
    },
    {
      "test": "/wai-aria/cell_aria-rowspan_2_on_div-manual.html",
      "subtests": [
        {
          "name": "cell aria-rowspan 2 on div",
          "status": "PASS",
          "message": null
        }
      ],
      "status": "OK",
      "message": null
    },
    {
      "test": "/wai-aria/cell_aria-rowspan_2_on_td_html_rowspan_3-manual.html",
      "subtests": [
        {
          "name": "cell aria-rowspan 2 on td html rowspan 3",
          "status": "FAIL",
          "message": "assert_true: \"property objectAttributes doesNotContain rowspan:2\" failed ;  expected true got false"
        }
      ],
      "status": "OK",
      "message": null
    },
    {
      "test": "/wai-aria/cell_aria-rowspan_2_on_td_html_rowspan_3_with_three_actual_rows-manual.html",
      "subtests": [
        {
          "name": "cell aria-rowspan 2 on td html rowspan 3 with three actual rows",
          "status": "FAIL",
          "message": "assert_true: \"property objectAttributes doesNotContain rowspan:2\" failed ;  expected true got false"
        }
      ],
      "status": "OK",
      "message": null
    },
    {
      "test": "/wai-aria/cell_aria-rowspan_2_on_td_with_html_rowspan_not_specified-manual.html",
      "subtests": [
        {
          "name": "cell aria-rowspan 2 on td with html rowspan not specified",
          "status": "PASS",
          "message": null
        }
      ],
      "status": "OK",
      "message": null
    },
    {
      "test": "/wai-aria/cell_colindex_4-manual.html",
      "subtests": [
        {
          "name": "cell colindex 4",
          "status": "PASS",
          "message": null
        }
      ],
      "status": "OK",
      "message": null
    },
    {
      "test": "/wai-aria/cell_rowindex_4-manual.html",
      "subtests": [
        {
          "name": "cell rowindex 4",
          "status": "PASS",
          "message": null
        }
      ],
      "status": "OK",
      "message": null
    },
    {
      "test": "/wai-aria/checkbox_readonly_false-manual.html",
      "subtests": [
        {
          "name": "checkbox readonly false",
          "status": "FAIL",
          "message": "assert_true: \"property states contains IA2_STATE_EDITABLE\" failed ;  expected true got false"
        }
      ],
      "status": "OK",
      "message": null
    },
    {
      "test": "/wai-aria/checkbox_readonly_true-manual.html",
      "subtests": [
        {
          "name": "checkbox readonly true",
          "status": "PASS",
          "message": null
        }
      ],
      "status": "OK",
      "message": null
    },
    {
      "test": "/wai-aria/checkbox_readonly_unspecified-manual.html",
      "subtests": [
        {
          "name": "checkbox readonly unspecified",
          "status": "FAIL",
          "message": "assert_true: \"property states contains IA2_STATE_EDITABLE\" failed ;  expected true got false"
        }
      ],
      "status": "OK",
      "message": null
    },
    {
      "test": "/wai-aria/columnheader_aria-colspan_2_on_div-manual.html",
      "subtests": [
        {
          "name": "columnheader aria-colspan 2 on div",
          "status": "PASS",
          "message": null
        }
      ],
      "status": "OK",
      "message": null
    },
    {
      "test": "/wai-aria/columnheader_aria-colspan_2_on_th_html_colspan_3-manual.html",
      "subtests": [
        {
          "name": "columnheader aria-colspan 2 on th html colspan 3",
          "status": "FAIL",
          "message": "assert_true: \"property objectAttributes doesNotContain colspan:2\" failed ;  expected true got false"
        }
      ],
      "status": "OK",
      "message": null
    },
    {
      "test": "/wai-aria/columnheader_aria-colspan_2_on_th_html_colspan_3_with_three_actual_columns-manual.html",
      "subtests": [
        {
          "name": "columnheader aria-colspan 2 on th html colspan 3 with three actual columns",
          "status": "FAIL",
          "message": "assert_true: \"property objectAttributes doesNotContain colspan:2\" failed ;  expected true got false"
        }
      ],
      "status": "OK",
      "message": null
    },
    {
      "test": "/wai-aria/columnheader_aria-colspan_2_on_th_with_html_colspan_not_specified-manual.html",
      "subtests": [
        {
          "name": "columnheader aria-colspan 2 on th with html colspan not specified",
          "status": "PASS",
          "message": null
        }
      ],
      "status": "OK",
      "message": null
    },
    {
      "test": "/wai-aria/columnheader_aria-rowspan_2_on_div-manual.html",
      "subtests": [
        {
          "name": "columnheader aria-rowspan 2 on div",
          "status": "PASS",
          "message": null
        }
      ],
      "status": "OK",
      "message": null
    },
    {
      "test": "/wai-aria/columnheader_aria-rowspan_2_on_th_html_rowspan_3-manual.html",
      "subtests": [
        {
          "name": "columnheader aria-rowspan 2 on th html rowspan 3",
          "status": "FAIL",
          "message": "assert_true: \"property objectAttributes doesNotContain rowspan:2\" failed ;  expected true got false"
        }
      ],
      "status": "OK",
      "message": null
    },
    {
      "test": "/wai-aria/columnheader_aria-rowspan_2_on_th_html_rowspan_3_with_three_actual_rows-manual.html",
      "subtests": [
        {
          "name": "columnheader aria-rowspan 2 on th html rowspan 3 with three actual rows",
          "status": "FAIL",
          "message": "assert_true: \"property objectAttributes doesNotContain rowspan:2\" failed ;  expected true got false"
        }
      ],
      "status": "OK",
      "message": null
    },
    {
      "test": "/wai-aria/columnheader_aria-rowspan_2_on_th_with_html_rowspan_not_specified-manual.html",
      "subtests": [
        {
          "name": "columnheader aria-rowspan 2 on th with html rowspan not specified",
          "status": "PASS",
          "message": null
        }
      ],
      "status": "OK",
      "message": null
    },
    {
      "test": "/wai-aria/columnheader_colindex_4-manual.html",
      "subtests": [
        {
          "name": "columnheader colindex 4",
          "status": "PASS",
          "message": null
        }
      ],
      "status": "OK",
      "message": null
    },
    {
      "test": "/wai-aria/columnheader_rowindex_4-manual.html",
      "subtests": [
        {
          "name": "columnheader rowindex 4",
          "status": "PASS",
          "message": null
        }
      ],
      "status": "OK",
      "message": null
    },
    {
      "test": "/wai-aria/columnheader_selected_false_not_automatically_propagated-manual.html",
      "subtests": [],
      "status": "NOTRUN",
      "message": "No steps for AT API IAccessible2"
    },
    {
      "test": "/wai-aria/columnheader_selected_true_not_automatically_propagated-manual.html",
      "subtests": [],
      "status": "NOTRUN",
      "message": "No steps for AT API IAccessible2"
    },
    {
      "test": "/wai-aria/combobox_controls_an_invalid_id-manual.html",
      "subtests": [
        {
          "name": "combobox controls an invalid ID",
          "status": "PASS",
          "message": null
        },
        {
          "name": "combobox controls an invalid ID 1",
          "status": "PASS",
          "message": null
        }
      ],
      "status": "OK",
      "message": null
    },
    {
      "test": "/wai-aria/combobox_haspopup_dialog-manual.html",
      "subtests": [
        {
          "name": "combobox haspopup dialog",
          "status": "PASS",
          "message": null
        }
      ],
      "status": "OK",
      "message": null
    },
    {
      "test": "/wai-aria/combobox_haspopup_false-manual.html",
      "subtests": [
        {
          "name": "combobox haspopup false",
          "status": "FAIL",
          "message": "assert_true: \"property objectAttributes contains haspopup:false\" failed ;  expected true got false"
        }
      ],
      "status": "OK",
      "message": null
    },
    {
      "test": "/wai-aria/combobox_haspopup_grid-manual.html",
      "subtests": [
        {
          "name": "combobox haspopup grid",
          "status": "PASS",
          "message": null
        }
      ],
      "status": "OK",
      "message": null
    },
    {
      "test": "/wai-aria/combobox_haspopup_listbox-manual.html",
      "subtests": [
        {
          "name": "combobox haspopup listbox",
          "status": "PASS",
          "message": null
        }
      ],
      "status": "OK",
      "message": null
    },
    {
      "test": "/wai-aria/combobox_haspopup_menu-manual.html",
      "subtests": [
        {
          "name": "combobox haspopup menu",
          "status": "PASS",
          "message": null
        }
      ],
      "status": "OK",
      "message": null
    },
    {
      "test": "/wai-aria/combobox_haspopup_tree-manual.html",
      "subtests": [
        {
          "name": "combobox haspopup tree",
          "status": "PASS",
          "message": null
        }
      ],
      "status": "OK",
      "message": null
    },
    {
      "test": "/wai-aria/combobox_haspopup_true-manual.html",
      "subtests": [
        {
          "name": "combobox haspopup true",
          "status": "PASS",
          "message": null
        }
      ],
      "status": "OK",
      "message": null
    },
    {
      "test": "/wai-aria/combobox_haspopup_unspecified-manual.html",
      "subtests": [
        {
          "name": "combobox haspopup unspecified",
          "status": "FAIL",
          "message": "assert_true: \"property objectAttributes contains haspopup:listbox\" failed ;  expected true got false"
        }
      ],
      "status": "OK",
      "message": null
    },
    {
      "test": "/wai-aria/combobox_orientation_horizontal-manual.html",
      "subtests": [
        {
          "name": "combobox orientation horizontal",
          "status": "PASS",
          "message": null
        }
      ],
      "status": "OK",
      "message": null
    },
    {
      "test": "/wai-aria/combobox_orientation_unspecified-manual.html",
      "subtests": [
        {
          "name": "combobox orientation unspecified",
          "status": "PASS",
          "message": null
        }
      ],
      "status": "OK",
      "message": null
    },
    {
      "test": "/wai-aria/combobox_orientation_vertical-manual.html",
      "subtests": [
        {
          "name": "combobox orientation vertical",
          "status": "PASS",
          "message": null
        }
      ],
      "status": "OK",
      "message": null
    },
    {
      "test": "/wai-aria/combobox_readonly_false-manual.html",
      "subtests": [
        {
          "name": "combobox readonly false",
          "status": "FAIL",
          "message": "assert_true: \"property states contains IA2_STATE_EDITABLE\" failed ;  expected true got false"
        }
      ],
      "status": "OK",
      "message": null
    },
    {
      "test": "/wai-aria/combobox_readonly_true-manual.html",
      "subtests": [
        {
          "name": "combobox readonly true",
          "status": "PASS",
          "message": null
        }
      ],
      "status": "OK",
      "message": null
    },
    {
      "test": "/wai-aria/combobox_readonly_unspecified-manual.html",
      "subtests": [
        {
          "name": "combobox readonly unspecified",
          "status": "FAIL",
          "message": "assert_true: \"property states contains IA2_STATE_EDITABLE\" failed ;  expected true got false"
        }
      ],
      "status": "OK",
      "message": null
    },
    {
      "test": "/wai-aria/dialog_modal_false-manual.html",
      "subtests": [
        {
          "name": "dialog modal false",
          "status": "PASS",
          "message": null
        },
        {
          "name": "dialog modal false 1",
          "status": "FAIL",
          "message": "assert_false: NOTRUN: No assertion for API IAccessible2 expected false got true"
        }
      ],
      "status": "OK",
      "message": null
    },
    {
      "test": "/wai-aria/dialog_modal_true-manual.html",
      "subtests": [
        {
          "name": "dialog modal true",
          "status": "PASS",
          "message": null
        },
        {
          "name": "dialog modal true 1",
          "status": "FAIL",
          "message": "assert_false: NOTRUN: No assertion for API IAccessible2 expected false got true"
        }
      ],
      "status": "OK",
      "message": null
    },
    {
      "test": "/wai-aria/dialog_modal_unspecified-manual.html",
      "subtests": [
        {
          "name": "dialog modal unspecified",
          "status": "PASS",
          "message": null
        },
        {
          "name": "dialog modal unspecified 1",
          "status": "FAIL",
          "message": "assert_false: NOTRUN: No assertion for API IAccessible2 expected false got true"
        }
      ],
      "status": "OK",
      "message": null
    },
    {
      "test": "/wai-aria/div_element_without_role_roledescription_valid-manual.html",
      "subtests": [
        {
          "name": "div element without role roledescription valid",
          "status": "FAIL",
          "message": "assert_true: \"property localizedExtendedRole is null\" failed ; \"property interfaces contains IAccessibleText2\" failed ; \"property interfaces contains IAccessibleHypertext2\" failed ;  expected true got false"
        }
      ],
      "status": "OK",
      "message": null
    },
    {
      "test": "/wai-aria/errormessage_object_in_invalid_state-manual.html",
      "subtests": [
        {
          "name": "errormessage object in invalid state",
          "status": "FAIL",
          "message": "assert_true: \"properties relations contains IA2_RELATION_ERROR_MESSAGE\" failed ERROR: [u'properties', u'relations', u'contains', u'IA2_RELATION_ERROR_MESSAGE'] is not a valid assertion;  expected true got false"
        },
        {
          "name": "errormessage object in invalid state 1",
          "status": "PASS",
          "message": null
        }
      ],
      "status": "OK",
      "message": null
    },
    {
      "test": "/wai-aria/errormessage_object_in_valid_state-manual.html",
      "subtests": [
        {
          "name": "errormessage object in valid state",
          "status": "PASS",
          "message": null
        },
        {
          "name": "errormessage object in valid state 1",
          "status": "FAIL",
          "message": "assert_true: \"property relations doesNotContain IA2_RELATION_ERROR_FOR\" failed ;  expected true got false"
        }
      ],
      "status": "OK",
      "message": null
    },
    {
      "test": "/wai-aria/feed-manual.html",
      "subtests": [
        {
          "name": "feed",
          "status": "PASS",
          "message": null
        }
      ],
      "status": "OK",
      "message": null
    },
    {
      "test": "/wai-aria/figure-manual.html",
      "subtests": [
        {
          "name": "figure",
          "status": "PASS",
          "message": null
        }
      ],
      "status": "OK",
      "message": null
    },
    {
      "test": "/wai-aria/grid_aria-readonly_false_automatically_propagated-manual.html",
      "subtests": [
        {
          "name": "grid aria-readonly false automatically propagated",
          "status": "PASS",
          "message": null
        },
        {
          "name": "grid aria-readonly false automatically propagated 1",
          "status": "FAIL",
          "message": "assert_false: NOTRUN: No assertion for API IAccessible2 expected false got true"
        },
        {
          "name": "grid aria-readonly false automatically propagated 2",
          "status": "FAIL",
          "message": "assert_false: NOTRUN: No assertion for API IAccessible2 expected false got true"
        }
      ],
      "status": "OK",
      "message": null
    },
    {
      "test": "/wai-aria/grid_aria-readonly_true_automatically_propagated-manual.html",
      "subtests": [
        {
          "name": "grid aria-readonly true automatically propagated",
          "status": "PASS",
          "message": null
        },
        {
          "name": "grid aria-readonly true automatically propagated 1",
          "status": "FAIL",
          "message": "assert_false: NOTRUN: No assertion for API IAccessible2 expected false got true"
        },
        {
          "name": "grid aria-readonly true automatically propagated 2",
          "status": "FAIL",
          "message": "assert_false: NOTRUN: No assertion for API IAccessible2 expected false got true"
        }
      ],
      "status": "OK",
      "message": null
    },
    {
      "test": "/wai-aria/grid_busy_false-manual.html",
      "subtests": [
        {
          "name": "grid busy false",
          "status": "PASS",
          "message": null
        }
      ],
      "status": "OK",
      "message": null
    },
    {
      "test": "/wai-aria/grid_busy_true-manual.html",
      "subtests": [
        {
          "name": "grid busy true",
          "status": "PASS",
          "message": null
        }
      ],
      "status": "OK",
      "message": null
    },
    {
      "test": "/wai-aria/grid_busy_value_changes-manual.html",
      "subtests": [
        {
          "name": "grid busy value changes",
          "status": "PASS",
          "message": null
        }
      ],
      "status": "OK",
      "message": null
    },
    {
      "test": "/wai-aria/grid_colcount_8-manual.html",
      "subtests": [
        {
          "name": "grid colcount 8",
          "status": "PASS",
          "message": null
        }
      ],
      "status": "OK",
      "message": null
    },
    {
      "test": "/wai-aria/grid_columnheader_readonly_false-manual.html",
      "subtests": [
        {
          "name": "grid columnheader readonly false",
          "status": "PASS",
          "message": null
        }
      ],
      "status": "OK",
      "message": null
    },
    {
      "test": "/wai-aria/grid_columnheader_readonly_true-manual.html",
      "subtests": [
        {
          "name": "grid columnheader readonly true",
          "status": "PASS",
          "message": null
        }
      ],
      "status": "OK",
      "message": null
    },
    {
      "test": "/wai-aria/grid_columnheader_readonly_unspecified-manual.html",
      "subtests": [],
      "status": "NOTRUN",
      "message": "No steps for AT API IAccessible2"
    },
    {
      "test": "/wai-aria/grid_columnheader_required_false-manual.html",
      "subtests": [
        {
          "name": "grid columnheader required false",
          "status": "PASS",
          "message": null
        }
      ],
      "status": "OK",
      "message": null
    },
    {
      "test": "/wai-aria/grid_columnheader_required_true-manual.html",
      "subtests": [
        {
          "name": "grid columnheader required true",
          "status": "PASS",
          "message": null
        }
      ],
      "status": "OK",
      "message": null
    },
    {
      "test": "/wai-aria/grid_columnheader_required_unspecified-manual.html",
      "subtests": [
        {
          "name": "grid columnheader required unspecified",
          "status": "PASS",
          "message": null
        }
      ],
      "status": "OK",
      "message": null
    },
    {
      "test": "/wai-aria/grid_rowcount_3-manual.html",
      "subtests": [
        {
          "name": "grid rowcount 3",
          "status": "PASS",
          "message": null
        }
      ],
      "status": "OK",
      "message": null
    },
    {
      "test": "/wai-aria/grid_rowheader_readonly_false-manual.html",
      "subtests": [],
      "status": "NOTRUN",
      "message": "No steps for AT API IAccessible2"
    },
    {
      "test": "/wai-aria/grid_rowheader_readonly_true-manual.html",
      "subtests": [],
      "status": "NOTRUN",
      "message": "No steps for AT API IAccessible2"
    },
    {
      "test": "/wai-aria/grid_rowheader_readonly_unspecified-manual.html",
      "subtests": [],
      "status": "NOTRUN",
      "message": "No steps for AT API IAccessible2"
    },
    {
      "test": "/wai-aria/grid_rowheader_required_false-manual.html",
      "subtests": [
        {
          "name": "grid rowheader required false",
          "status": "PASS",
          "message": null
        }
      ],
      "status": "OK",
      "message": null
    },
    {
      "test": "/wai-aria/grid_rowheader_required_true-manual.html",
      "subtests": [
        {
          "name": "grid rowheader required true",
          "status": "PASS",
          "message": null
        }
      ],
      "status": "OK",
      "message": null
    },
    {
      "test": "/wai-aria/grid_rowheader_required_unspecified-manual.html",
      "subtests": [
        {
          "name": "grid rowheader required unspecified",
          "status": "PASS",
          "message": null
        }
      ],
      "status": "OK",
      "message": null
    },
    {
      "test": "/wai-aria/gridcell_aria-colspan_2_on_div-manual.html",
      "subtests": [
        {
          "name": "gridcell aria-colspan 2 on div",
          "status": "PASS",
          "message": null
        }
      ],
      "status": "OK",
      "message": null
    },
    {
      "test": "/wai-aria/gridcell_aria-rowspan_2_on_div-manual.html",
      "subtests": [
        {
          "name": "gridcell aria-rowspan 2 on div",
          "status": "PASS",
          "message": null
        }
      ],
      "status": "OK",
      "message": null
    },
    {
      "test": "/wai-aria/gridcell_colindex_4-manual.html",
      "subtests": [
        {
          "name": "gridcell colindex 4",
          "status": "PASS",
          "message": null
        }
      ],
      "status": "OK",
      "message": null
    },
    {
      "test": "/wai-aria/gridcell_rowindex_4-manual.html",
      "subtests": [
        {
          "name": "gridcell rowindex 4",
          "status": "PASS",
          "message": null
        }
      ],
      "status": "OK",
      "message": null
    },
    {
      "test": "/wai-aria/group_hidden_undefined_element_not_rendered-manual.html",
      "subtests": [
        {
          "name": "group hidden undefined element not rendered",
          "status": "FAIL",
          "message": "assert_true: ATTA returned ERROR with message:  expected true got false"
        }
      ],
      "status": "OK",
      "message": null
    },
    {
      "test": "/wai-aria/group_hidden_undefined_element_rendered-manual.html",
      "subtests": [
        {
          "name": "group hidden undefined element rendered",
          "status": "PASS",
          "message": null
        }
      ],
      "status": "OK",
      "message": null
    },
    {
      "test": "/wai-aria/heading_level_unspecified-manual.html",
      "subtests": [
        {
          "name": "heading level unspecified",
          "status": "FAIL",
          "message": "assert_true: \"property objectAttributes contains level:2\" failed ;  expected true got false"
        }
      ],
      "status": "OK",
      "message": null
    },
    {
      "test": "/wai-aria/keyshortcuts_multiple_shortcuts-manual.html",
      "subtests": [],
      "status": "NOTRUN",
      "message": "No steps for AT API IAccessible2"
    },
    {
      "test": "/wai-aria/keyshortcuts_one_shortcut-manual.html",
      "subtests": [],
      "status": "NOTRUN",
      "message": "No steps for AT API IAccessible2"
    },
    {
      "test": "/wai-aria/listbox_busy_false-manual.html",
      "subtests": [],
      "status": "NOTRUN",
      "message": "No steps for AT API IAccessible2"
    },
    {
      "test": "/wai-aria/listbox_busy_true-manual.html",
      "subtests": [],
      "status": "NOTRUN",
      "message": "No steps for AT API IAccessible2"
    },
    {
      "test": "/wai-aria/listbox_orientation_horizontal-manual.html",
      "subtests": [
        {
          "name": "listbox orientation horizontal",
          "status": "PASS",
          "message": null
        }
      ],
      "status": "OK",
      "message": null
    },
    {
      "test": "/wai-aria/listbox_orientation_unspecified-manual.html",
      "subtests": [
        {
          "name": "listbox orientation unspecified",
          "status": "PASS",
          "message": null
        }
      ],
      "status": "OK",
      "message": null
    },
    {
      "test": "/wai-aria/listbox_orientation_vertical-manual.html",
      "subtests": [
        {
          "name": "listbox orientation vertical",
          "status": "PASS",
          "message": null
        }
      ],
      "status": "OK",
      "message": null
    },
    {
      "test": "/wai-aria/listbox_readonly_false-manual.html",
      "subtests": [
        {
          "name": "listbox readonly false",
          "status": "FAIL",
          "message": "assert_true: \"property states contains IA2_STATE_EDITABLE\" failed ;  expected true got false"
        }
      ],
      "status": "OK",
      "message": null
    },
    {
      "test": "/wai-aria/listbox_readonly_true-manual.html",
      "subtests": [
        {
          "name": "listbox readonly true",
          "status": "PASS",
          "message": null
        }
      ],
      "status": "OK",
      "message": null
    },
    {
      "test": "/wai-aria/listbox_readonly_unspecified-manual.html",
      "subtests": [
        {
          "name": "listbox readonly unspecified",
          "status": "FAIL",
          "message": "assert_true: \"property states contains IA2_STATE_EDITABLE\" failed ;  expected true got false"
        }
      ],
      "status": "OK",
      "message": null
    },
    {
      "test": "/wai-aria/listitem_setsize_-1-manual.html",
      "subtests": [
        {
          "name": "listitem setsize -1",
          "status": "FAIL",
          "message": "assert_true: \"property objectAttributes contains setsize:-1\" failed ; \"property groupPosition contains similarItemsInGroup:-1\" failed ;  expected true got false"
        }
      ],
      "status": "OK",
      "message": null
    },
    {
      "test": "/wai-aria/menu_orientation_horizontal-manual.html",
      "subtests": [
        {
          "name": "menu orientation horizontal",
          "status": "PASS",
          "message": null
        }
      ],
      "status": "OK",
      "message": null
    },
    {
      "test": "/wai-aria/menu_orientation_unspecified-manual.html",
      "subtests": [
        {
          "name": "menu orientation unspecified",
          "status": "PASS",
          "message": null
        }
      ],
      "status": "OK",
      "message": null
    },
    {
      "test": "/wai-aria/menu_orientation_vertical-manual.html",
      "subtests": [
        {
          "name": "menu orientation vertical",
          "status": "PASS",
          "message": null
        }
      ],
      "status": "OK",
      "message": null
    },
    {
      "test": "/wai-aria/menubar_busy_false-manual.html",
      "subtests": [
        {
          "name": "menubar busy false",
          "status": "PASS",
          "message": null
        }
      ],
      "status": "OK",
      "message": null
    },
    {
      "test": "/wai-aria/menubar_busy_true-manual.html",
      "subtests": [
        {
          "name": "menubar busy true",
          "status": "PASS",
          "message": null
        }
      ],
      "status": "OK",
      "message": null
    },
    {
      "test": "/wai-aria/menubar_orientation_horizontal-manual.html",
      "subtests": [
        {
          "name": "menubar orientation horizontal",
          "status": "PASS",
          "message": null
        }
      ],
      "status": "OK",
      "message": null
    },
    {
      "test": "/wai-aria/menubar_orientation_unspecified-manual.html",
      "subtests": [
        {
          "name": "menubar orientation unspecified",
          "status": "PASS",
          "message": null
        }
      ],
      "status": "OK",
      "message": null
    },
    {
      "test": "/wai-aria/menubar_orientation_vertical-manual.html",
      "subtests": [
        {
          "name": "menubar orientation vertical",
          "status": "PASS",
          "message": null
        }
      ],
      "status": "OK",
      "message": null
    },
    {
      "test": "/wai-aria/menuitem_posinset_and_setsize-manual.html",
      "subtests": [
        {
          "name": "menuitem posinset and setsize",
          "status": "PASS",
          "message": null
        }
      ],
      "status": "OK",
      "message": null
    },
    {
      "test": "/wai-aria/menuitemcheckbox_posinset_and_setsize-manual.html",
      "subtests": [
        {
          "name": "menuitemcheckbox posinset and setsize",
          "status": "PASS",
          "message": null
        }
      ],
      "status": "OK",
      "message": null
    },
    {
      "test": "/wai-aria/menuitemcheckbox_readonly_false-manual.html",
      "subtests": [
        {
          "name": "menuitemcheckbox readonly false",
          "status": "FAIL",
          "message": "assert_true: \"property states contains IA2_STATE_EDITABLE\" failed ;  expected true got false"
        }
      ],
      "status": "OK",
      "message": null
    },
    {
      "test": "/wai-aria/menuitemcheckbox_readonly_true-manual.html",
      "subtests": [
        {
          "name": "menuitemcheckbox readonly true",
          "status": "FAIL",
          "message": "assert_true: \"property states contains IA2_STATE_EDITABLE\" failed ;  expected true got false"
        }
      ],
      "status": "OK",
      "message": null
    },
    {
      "test": "/wai-aria/menuitemcheckbox_readonly_unspecified-manual.html",
      "subtests": [
        {
          "name": "menuitemcheckbox readonly unspecified",
          "status": "FAIL",
          "message": "assert_true: \"property states contains IA2_STATE_EDITABLE\" failed ;  expected true got false"
        }
      ],
      "status": "OK",
      "message": null
    },
    {
      "test": "/wai-aria/menuitemradio_posinset_and_setsize-manual.html",
      "subtests": [
        {
          "name": "menuitemradio posinset and setsize",
          "status": "PASS",
          "message": null
        }
      ],
      "status": "OK",
      "message": null
    },
    {
      "test": "/wai-aria/menuitemradio_readonly_false-manual.html",
      "subtests": [
        {
          "name": "menuitemradio readonly false",
          "status": "FAIL",
          "message": "assert_true: \"property states contains IA2_STATE_EDITABLE\" failed ;  expected true got false"
        }
      ],
      "status": "OK",
      "message": null
    },
    {
      "test": "/wai-aria/menuitemradio_readonly_true-manual.html",
      "subtests": [
        {
          "name": "menuitemradio readonly true",
          "status": "PASS",
          "message": null
        }
      ],
      "status": "OK",
      "message": null
    },
    {
      "test": "/wai-aria/menuitemradio_readonly_unspecified-manual.html",
      "subtests": [
        {
          "name": "menuitemradio readonly unspecified",
          "status": "FAIL",
          "message": "assert_true: \"property states contains IA2_STATE_EDITABLE\" failed ;  expected true got false"
        }
      ],
      "status": "OK",
      "message": null
    },
    {
      "test": "/wai-aria/none-manual.html",
      "subtests": [
        {
          "name": "none",
          "status": "FAIL",
          "message": "assert_true: ATTA returned ERROR with message:  expected true got false"
        }
      ],
      "status": "OK",
      "message": null
    },
    {
      "test": "/wai-aria/option_selected_false-manual.html",
      "subtests": [],
      "status": "NOTRUN",
      "message": "No steps for AT API IAccessible2"
    },
    {
      "test": "/wai-aria/option_selected_true-manual.html",
      "subtests": [],
      "status": "NOTRUN",
      "message": "No steps for AT API IAccessible2"
    },
    {
      "test": "/wai-aria/option_selected_undefined-manual.html",
      "subtests": [],
      "status": "NOTRUN",
      "message": "No steps for AT API IAccessible2"
    },
    {
      "test": "/wai-aria/option_selected_value_changes-manual.html",
      "subtests": [],
      "status": "NOTRUN",
      "message": "No steps for AT API IAccessible2"
    },
    {
      "test": "/wai-aria/radiogroup_orientation_horizontal-manual.html",
      "subtests": [
        {
          "name": "radiogroup orientation horizontal",
          "status": "PASS",
          "message": null
        }
      ],
      "status": "OK",
      "message": null
    },
    {
      "test": "/wai-aria/radiogroup_orientation_unspecified-manual.html",
      "subtests": [
        {
          "name": "radiogroup orientation unspecified",
          "status": "PASS",
          "message": null
        }
      ],
      "status": "OK",
      "message": null
    },
    {
      "test": "/wai-aria/radiogroup_orientation_vertical-manual.html",
      "subtests": [
        {
          "name": "radiogroup orientation vertical",
          "status": "PASS",
          "message": null
        }
      ],
      "status": "OK",
      "message": null
    },
    {
      "test": "/wai-aria/radiogroup_readonly_false-manual.html",
      "subtests": [
        {
          "name": "radiogroup readonly false",
          "status": "FAIL",
          "message": "assert_true: \"property states contains IA2_STATE_EDITABLE\" failed ;  expected true got false"
        }
      ],
      "status": "OK",
      "message": null
    },
    {
      "test": "/wai-aria/radiogroup_readonly_true-manual.html",
      "subtests": [
        {
          "name": "radiogroup readonly true",
          "status": "PASS",
          "message": null
        }
      ],
      "status": "OK",
      "message": null
    },
    {
      "test": "/wai-aria/radiogroup_readonly_unspecified-manual.html",
      "subtests": [
        {
          "name": "radiogroup readonly unspecified",
          "status": "FAIL",
          "message": "assert_true: \"property states contains IA2_STATE_EDITABLE\" failed ;  expected true got false"
        }
      ],
      "status": "OK",
      "message": null
    },
    {
      "test": "/wai-aria/region_with_name-manual.html",
      "subtests": [
        {
          "name": "region with name",
          "status": "PASS",
          "message": null
        }
      ],
      "status": "OK",
      "message": null
    },
    {
      "test": "/wai-aria/region_without_name-manual.html",
      "subtests": [
        {
          "name": "region without name",
          "status": "FAIL",
          "message": "assert_true: \"property interfaces contains IAccessibleText2\" failed ; \"property interfaces contains IAccessibleHypertext2\" failed ;  expected true got false"
        }
      ],
      "status": "OK",
      "message": null
    },
    {
      "test": "/wai-aria/row_colindex_4-manual.html",
      "subtests": [
        {
          "name": "row colindex 4",
          "status": "PASS",
          "message": null
        },
        {
          "name": "row colindex 4 1",
          "status": "FAIL",
          "message": "assert_false: NOTRUN: No assertion for API IAccessible2 expected false got true"
        }
      ],
      "status": "OK",
      "message": null
    },
    {
      "test": "/wai-aria/row_rowindex_4-manual.html",
      "subtests": [
        {
          "name": "row rowindex 4",
          "status": "PASS",
          "message": null
        },
        {
          "name": "row rowindex 4 1",
          "status": "FAIL",
          "message": "assert_false: NOTRUN: No assertion for API IAccessible2 expected false got true"
        }
      ],
      "status": "OK",
      "message": null
    },
    {
      "test": "/wai-aria/rowheader_aria-colspan_2_on_div-manual.html",
      "subtests": [
        {
          "name": "rowheader aria-colspan 2 on div",
          "status": "PASS",
          "message": null
        }
      ],
      "status": "OK",
      "message": null
    },
    {
      "test": "/wai-aria/rowheader_aria-rowspan_2_on_div-manual.html",
      "subtests": [
        {
          "name": "rowheader aria-rowspan 2 on div",
          "status": "PASS",
          "message": null
        }
      ],
      "status": "OK",
      "message": null
    },
    {
      "test": "/wai-aria/rowheader_colindex_4-manual.html",
      "subtests": [
        {
          "name": "rowheader colindex 4",
          "status": "PASS",
          "message": null
        }
      ],
      "status": "OK",
      "message": null
    },
    {
      "test": "/wai-aria/rowheader_rowindex_4-manual.html",
      "subtests": [
        {
          "name": "rowheader rowindex 4",
          "status": "PASS",
          "message": null
        }
      ],
      "status": "OK",
      "message": null
    },
    {
      "test": "/wai-aria/rowheader_selected_false_not_automatically_propagated-manual.html",
      "subtests": [],
      "status": "NOTRUN",
      "message": "No steps for AT API IAccessible2"
    },
    {
      "test": "/wai-aria/rowheader_selected_true_not_automatically_propagated-manual.html",
      "subtests": [],
      "status": "NOTRUN",
      "message": "No steps for AT API IAccessible2"
    },
    {
      "test": "/wai-aria/scrollbar_all_values_unspecified-manual.html",
      "subtests": [
        {
          "name": "scrollbar all values unspecified",
          "status": "FAIL",
          "message": "assert_true: \"property interfaces contains AccessibleValue\" failed ; \"property minimumValue is 0\" failed ; \"property currentValue is 50\" failed ; \"property maximumValue is 100\" failed ;  expected true got false"
        }
      ],
      "status": "OK",
      "message": null
    },
    {
      "test": "/wai-aria/scrollbar_only_valuenow_unspecified-manual.html",
      "subtests": [
        {
          "name": "scrollbar only valuenow unspecified",
          "status": "FAIL",
          "message": "assert_true: \"property interfaces contains AccessibleValue\" failed ; \"property currentValue is 20\" failed ;  expected true got false"
        }
      ],
      "status": "OK",
      "message": null
    },
    {
      "test": "/wai-aria/scrollbar_orientation_unspecified-manual.html",
      "subtests": [
        {
          "name": "scrollbar orientation unspecified",
          "status": "PASS",
          "message": null
        }
      ],
      "status": "OK",
      "message": null
    },
    {
      "test": "/wai-aria/searchbox-manual.html",
      "subtests": [
        {
          "name": "searchbox",
          "status": "PASS",
          "message": null
        }
      ],
      "status": "OK",
      "message": null
    },
    {
      "test": "/wai-aria/searchbox_activedescendant-manual.html",
      "subtests": [
        {
          "name": "searchbox activedescendant",
          "status": "PASS",
          "message": null
        },
        {
          "name": "searchbox activedescendant 1",
          "status": "FAIL",
          "message": "assert_false: NOTRUN: No assertion for API IAccessible2 expected false got true"
        }
      ],
      "status": "OK",
      "message": null
    },
    {
      "test": "/wai-aria/searchbox_activedescendant_value_changes-manual.html",
      "subtests": [
        {
          "name": "searchbox activedescendant value changes",
          "status": "PASS",
          "message": null
        },
        {
          "name": "searchbox activedescendant value changes 1",
          "status": "FAIL",
          "message": "assert_false: NOTRUN: No assertion for API IAccessible2 expected false got true"
        }
      ],
      "status": "OK",
      "message": null
    },
    {
      "test": "/wai-aria/searchbox_autocomplete_both-manual.html",
      "subtests": [
        {
          "name": "searchbox autocomplete both",
          "status": "PASS",
          "message": null
        }
      ],
      "status": "OK",
      "message": null
    },
    {
      "test": "/wai-aria/searchbox_autocomplete_inline-manual.html",
      "subtests": [
        {
          "name": "searchbox autocomplete inline",
          "status": "PASS",
          "message": null
        }
      ],
      "status": "OK",
      "message": null
    },
    {
      "test": "/wai-aria/searchbox_autocomplete_list-manual.html",
      "subtests": [
        {
          "name": "searchbox autocomplete list",
          "status": "PASS",
          "message": null
        }
      ],
      "status": "OK",
      "message": null
    },
    {
      "test": "/wai-aria/searchbox_autocomplete_none-manual.html",
      "subtests": [
        {
          "name": "searchbox autocomplete none",
          "status": "PASS",
          "message": null
        }
      ],
      "status": "OK",
      "message": null
    },
    {
      "test": "/wai-aria/searchbox_autocomplete_unspecified-manual.html",
      "subtests": [
        {
          "name": "searchbox autocomplete unspecified",
          "status": "FAIL",
          "message": "assert_true: \"property objectAttributes contains autocomplete:none\" failed ;  expected true got false"
        }
      ],
      "status": "OK",
      "message": null
    },
    {
      "test": "/wai-aria/searchbox_multiline_false-manual.html",
      "subtests": [
        {
          "name": "searchbox multiline false",
          "status": "FAIL",
          "message": "assert_true: \"property states contains IA2_SINGLE_LINE\" failed ;  expected true got false"
        }
      ],
      "status": "OK",
      "message": null
    },
    {
      "test": "/wai-aria/searchbox_multiline_true-manual.html",
      "subtests": [
        {
          "name": "searchbox multiline true",
          "status": "FAIL",
          "message": "assert_true: \"property states contains IA2_MULTI_LINE\" failed ;  expected true got false"
        }
      ],
      "status": "OK",
      "message": null
    },
    {
      "test": "/wai-aria/searchbox_multiline_unspecified-manual.html",
      "subtests": [
        {
          "name": "searchbox multiline unspecified",
          "status": "FAIL",
          "message": "assert_true: \"property objectAttributes contains xml-roles:search\" failed ;  expected true got false"
        }
      ],
      "status": "OK",
      "message": null
    },
    {
      "test": "/wai-aria/searchbox_placeholder-manual.html",
      "subtests": [
        {
          "name": "searchbox placeholder",
          "status": "FAIL",
          "message": "assert_true: \"property states doesNotContain IA2_STATE_SINGLE_LINE\" failed ; \"property objectAttributes contains placeholder-text:DD/MM/YYYY\" failed ;  expected true got false"
        }
      ],
      "status": "OK",
      "message": null
    },
    {
      "test": "/wai-aria/searchbox_readonly_false-manual.html",
      "subtests": [
        {
          "name": "searchbox readonly false",
          "status": "PASS",
          "message": null
        }
      ],
      "status": "OK",
      "message": null
    },
    {
      "test": "/wai-aria/searchbox_readonly_true-manual.html",
      "subtests": [
        {
          "name": "searchbox readonly true",
          "status": "PASS",
          "message": null
        }
      ],
      "status": "OK",
      "message": null
    },
    {
      "test": "/wai-aria/searchbox_readonly_unspecified-manual.html",
      "subtests": [
        {
          "name": "searchbox readonly unspecified",
          "status": "PASS",
          "message": null
        }
      ],
      "status": "OK",
      "message": null
    },
    {
      "test": "/wai-aria/searchbox_required_false-manual.html",
      "subtests": [
        {
          "name": "searchbox required false",
          "status": "PASS",
          "message": null
        }
      ],
      "status": "OK",
      "message": null
    },
    {
      "test": "/wai-aria/searchbox_required_true-manual.html",
      "subtests": [
        {
          "name": "searchbox required true",
          "status": "PASS",
          "message": null
        }
      ],
      "status": "OK",
      "message": null
    },
    {
      "test": "/wai-aria/searchbox_required_unspecified-manual.html",
      "subtests": [
        {
          "name": "searchbox required unspecified",
          "status": "PASS",
          "message": null
        }
      ],
      "status": "OK",
      "message": null
    },
    {
      "test": "/wai-aria/separator_focusable_all_values_unspecified-manual.html",
      "subtests": [
        {
          "name": "separator focusable all values unspecified",
          "status": "FAIL",
          "message": "assert_true: \"property interfaces contains AccessibleValue\" failed ; \"property minimumValue is 0\" failed ; \"property currentValue is 50\" failed ; \"property maximumValue is 100\" failed ;  expected true got false"
        }
      ],
      "status": "OK",
      "message": null
    },
    {
      "test": "/wai-aria/separator_focusable_only_valuenow_unspecified-manual.html",
      "subtests": [
        {
          "name": "separator focusable only valuenow unspecified",
          "status": "FAIL",
          "message": "assert_true: \"property interfaces contains AccessibleValue\" failed ; \"property currentValue is 50\" failed ;  expected true got false"
        }
      ],
      "status": "OK",
      "message": null
    },
    {
      "test": "/wai-aria/separator_focusable_valuetext-manual.html",
      "subtests": [
        {
          "name": "separator focusable valuetext",
          "status": "FAIL",
          "message": "assert_true: \"property interfaces contains AccessibleValue\" failed ; \"property minimumValue is 0\" failed ; \"property currentValue is 50\" failed ; \"property maximumValue is 100\" failed ;  expected true got false"
        }
      ],
      "status": "OK",
      "message": null
    },
    {
      "test": "/wai-aria/separator_orientation_unspecified-manual.html",
      "subtests": [
        {
          "name": "separator orientation unspecified",
          "status": "PASS",
          "message": null
        }
      ],
      "status": "OK",
      "message": null
    },
    {
      "test": "/wai-aria/separator_unfocusable_all_values_unspecified-manual.html",
      "subtests": [],
      "status": "NOTRUN",
      "message": "No steps for AT API IAccessible2"
    },
    {
      "test": "/wai-aria/separator_unfocusable_valuetext-manual.html",
      "subtests": [
        {
          "name": "separator unfocusable valuetext",
          "status": "PASS",
          "message": null
        }
      ],
      "status": "OK",
      "message": null
    },
    {
      "test": "/wai-aria/slider_all_values_unspecified-manual.html",
      "subtests": [
        {
          "name": "slider all values unspecified",
          "status": "FAIL",
          "message": "assert_true: \"property interfaces contains AccessibleValue\" failed ; \"property minimumValue is 0\" failed ; \"property currentValue is 50\" failed ; \"property maximumValue is 100\" failed ;  expected true got false"
        }
      ],
      "status": "OK",
      "message": null
    },
    {
      "test": "/wai-aria/slider_only_valuenow_unspecified-manual.html",
      "subtests": [
        {
          "name": "slider only valuenow unspecified",
          "status": "FAIL",
          "message": "assert_true: \"property interfaces contains AccessibleValue\" failed ; \"property currentValue is 20\" failed ;  expected true got false"
        }
      ],
      "status": "OK",
      "message": null
    },
    {
      "test": "/wai-aria/slider_orientation_unspecified-manual.html",
      "subtests": [
        {
          "name": "slider orientation unspecified",
          "status": "PASS",
          "message": null
        }
      ],
      "status": "OK",
      "message": null
    },
    {
      "test": "/wai-aria/slider_readonly_false-manual.html",
      "subtests": [
        {
          "name": "slider readonly false",
          "status": "FAIL",
          "message": "assert_true: \"property interfaces contains IAcesssibleValue\" failed ; \"property states contains IA2_STATE_EDITABLE\" failed ;  expected true got false"
        }
      ],
      "status": "OK",
      "message": null
    },
    {
      "test": "/wai-aria/slider_readonly_true-manual.html",
      "subtests": [
        {
          "name": "slider readonly true",
          "status": "FAIL",
          "message": "assert_true: \"property interfaces contains IAcesssibleValue\" failed ;  expected true got false"
        }
      ],
      "status": "OK",
      "message": null
    },
    {
      "test": "/wai-aria/slider_readonly_unspecified-manual.html",
      "subtests": [
        {
          "name": "slider readonly unspecified",
          "status": "FAIL",
          "message": "assert_true: \"property interfaces contains IAcesssibleValue\" failed ; \"property states contains IA2_STATE_EDITABLE\" failed ;  expected true got false"
        }
      ],
      "status": "OK",
      "message": null
    },
    {
      "test": "/wai-aria/spinbutton_all_values_unspecified-manual.html",
      "subtests": [
        {
          "name": "spinbutton all values unspecified",
          "status": "FAIL",
          "message": "assert_true: \"property interfaces contains AccessibleValue\" failed ; \"property minimumValue isLTE -9007199254740992\" failed ; \"property currentValue is 0\" failed ; \"property maximumValue isGTE 9007199254740992\" failed ;  expected true got false"
        }
      ],
      "status": "OK",
      "message": null
    },
    {
      "test": "/wai-aria/spinbutton_only_aria-valuenow_unspecified-manual.html",
      "subtests": [
        {
          "name": "spinbutton only aria-valuenow unspecified",
          "status": "FAIL",
          "message": "assert_true: \"property interfaces contains AccessibleValue\" failed ; \"property currentValue is 0\" failed ;  expected true got false"
        }
      ],
      "status": "OK",
      "message": null
    },
    {
      "test": "/wai-aria/spinbutton_readonly_false-manual.html",
      "subtests": [
        {
          "name": "spinbutton readonly false",
          "status": "FAIL",
          "message": "assert_true: \"property interfaces contains IAcesssibleValue\" failed ; \"property states contains IA2_STATE_EDITABLE\" failed ;  expected true got false"
        }
      ],
      "status": "OK",
      "message": null
    },
    {
      "test": "/wai-aria/spinbutton_readonly_true-manual.html",
      "subtests": [
        {
          "name": "spinbutton readonly true",
          "status": "FAIL",
          "message": "assert_true: \"property interfaces contains IAcesssibleValue\" failed ;  expected true got false"
        }
      ],
      "status": "OK",
      "message": null
    },
    {
      "test": "/wai-aria/spinbutton_readonly_unspecified-manual.html",
      "subtests": [
        {
          "name": "spinbutton readonly unspecified",
          "status": "FAIL",
          "message": "assert_true: \"property interfaces contains IAcesssibleValue\" failed ; \"property states contains IA2_STATE_EDITABLE\" failed ;  expected true got false"
        }
      ],
      "status": "OK",
      "message": null
    },
    {
      "test": "/wai-aria/switch_checked_false-manual.html",
      "subtests": [
        {
          "name": "switch checked false",
          "status": "PASS",
          "message": null
        }
      ],
      "status": "OK",
      "message": null
    },
    {
      "test": "/wai-aria/switch_checked_mixed-manual.html",
      "subtests": [
        {
          "name": "switch checked mixed",
          "status": "PASS",
          "message": null
        }
      ],
      "status": "OK",
      "message": null
    },
    {
      "test": "/wai-aria/switch_checked_true-manual.html",
      "subtests": [
        {
          "name": "switch checked true",
          "status": "PASS",
          "message": null
        }
      ],
      "status": "OK",
      "message": null
    },
    {
      "test": "/wai-aria/switch_checked_undefined-manual.html",
      "subtests": [
        {
          "name": "switch checked undefined",
          "status": "PASS",
          "message": null
        }
      ],
      "status": "OK",
      "message": null
    },
    {
      "test": "/wai-aria/switch_checked_value_changes-manual.html",
      "subtests": [
        {
          "name": "switch checked value changes",
          "status": "PASS",
          "message": null
        }
      ],
      "status": "OK",
      "message": null
    },
    {
      "test": "/wai-aria/switch_readonly_false-manual.html",
      "subtests": [
        {
          "name": "switch readonly false",
          "status": "FAIL",
          "message": "assert_true: \"property states contains IA2_STATE_EDITABLE\" failed ;  expected true got false"
        }
      ],
      "status": "OK",
      "message": null
    },
    {
      "test": "/wai-aria/switch_readonly_true-manual.html",
      "subtests": [
        {
          "name": "switch readonly true",
          "status": "PASS",
          "message": null
        }
      ],
      "status": "OK",
      "message": null
    },
    {
      "test": "/wai-aria/switch_readonly_unspecified-manual.html",
      "subtests": [
        {
          "name": "switch readonly unspecified",
          "status": "FAIL",
          "message": "assert_true: \"property states contains IA2_STATE_EDITABLE\" failed ;  expected true got false"
        }
      ],
      "status": "OK",
      "message": null
    },
    {
      "test": "/wai-aria/tab_posinset_and_setsize-manual.html",
      "subtests": [
        {
          "name": "tab posinset and setsize",
          "status": "PASS",
          "message": null
        }
      ],
      "status": "OK",
      "message": null
    },
    {
      "test": "/wai-aria/table_colcount_-1-manual.html",
      "subtests": [
        {
          "name": "table colcount -1",
          "status": "PASS",
          "message": null
        }
      ],
      "status": "OK",
      "message": null
    },
    {
      "test": "/wai-aria/table_colcount_8-manual.html",
      "subtests": [
        {
          "name": "table colcount 8",
          "status": "PASS",
          "message": null
        }
      ],
      "status": "OK",
      "message": null
    },
    {
      "test": "/wai-aria/table_rowcount_-1-manual.html",
      "subtests": [
        {
          "name": "table rowcount -1",
          "status": "PASS",
          "message": null
        }
      ],
      "status": "OK",
      "message": null
    },
    {
      "test": "/wai-aria/table_rowcount_3-manual.html",
      "subtests": [
        {
          "name": "table rowcount 3",
          "status": "PASS",
          "message": null
        }
      ],
      "status": "OK",
      "message": null
    },
    {
      "test": "/wai-aria/tablist_orientation_horizontal-manual.html",
      "subtests": [
        {
          "name": "tablist orientation horizontal",
          "status": "PASS",
          "message": null
        }
      ],
      "status": "OK",
      "message": null
    },
    {
      "test": "/wai-aria/tablist_orientation_unspecified-manual.html",
      "subtests": [
        {
          "name": "tablist orientation unspecified",
          "status": "PASS",
          "message": null
        }
      ],
      "status": "OK",
      "message": null
    },
    {
      "test": "/wai-aria/tablist_orientation_vertical-manual.html",
      "subtests": [
        {
          "name": "tablist orientation vertical",
          "status": "PASS",
          "message": null
        }
      ],
      "status": "OK",
      "message": null
    },
    {
      "test": "/wai-aria/term_role-manual.html",
      "subtests": [],
      "status": "NOTRUN",
      "message": "No steps for AT API IAccessible2"
    },
    {
      "test": "/wai-aria/textbox_placeholder-manual.html",
      "subtests": [
        {
          "name": "textbox placeholder",
          "status": "FAIL",
          "message": "assert_true: \"property states doesNotContain IA2_STATE_SINGLE_LINE\" failed ; \"property objectAttributes contains placeholder-text:DD/MM/YYYY\" failed ;  expected true got false"
        }
      ],
      "status": "OK",
      "message": null
    },
    {
      "test": "/wai-aria/toolbar_orientation_horizontal-manual.html",
      "subtests": [
        {
          "name": "toolbar orientation horizontal",
          "status": "PASS",
          "message": null
        }
      ],
      "status": "OK",
      "message": null
    },
    {
      "test": "/wai-aria/toolbar_orientation_unspecified-manual.html",
      "subtests": [
        {
          "name": "toolbar orientation unspecified",
          "status": "PASS",
          "message": null
        }
      ],
      "status": "OK",
      "message": null
    },
    {
      "test": "/wai-aria/toolbar_orientation_vertical-manual.html",
      "subtests": [
        {
          "name": "toolbar orientation vertical",
          "status": "PASS",
          "message": null
        }
      ],
      "status": "OK",
      "message": null
    },
    {
      "test": "/wai-aria/tree_orientation_horizontal-manual.html",
      "subtests": [
        {
          "name": "tree orientation horizontal",
          "status": "PASS",
          "message": null
        }
      ],
      "status": "OK",
      "message": null
    },
    {
      "test": "/wai-aria/tree_orientation_unspecified-manual.html",
      "subtests": [
        {
          "name": "tree orientation unspecified",
          "status": "PASS",
          "message": null
        }
      ],
      "status": "OK",
      "message": null
    },
    {
      "test": "/wai-aria/tree_orientation_vertical-manual.html",
      "subtests": [
        {
          "name": "tree orientation vertical",
          "status": "PASS",
          "message": null
        }
      ],
      "status": "OK",
      "message": null
    },
    {
      "test": "/wai-aria/treegrid_colcount_8-manual.html",
      "subtests": [
        {
          "name": "treegrid colcount 8",
          "status": "PASS",
          "message": null
        }
      ],
      "status": "OK",
      "message": null
    },
    {
      "test": "/wai-aria/treegrid_orientation_horizontal-manual.html",
      "subtests": [
        {
          "name": "treegrid orientation horizontal",
          "status": "PASS",
          "message": null
        }
      ],
      "status": "OK",
      "message": null
    },
    {
      "test": "/wai-aria/treegrid_orientation_unspecified-manual.html",
      "subtests": [
        {
          "name": "treegrid orientation unspecified",
          "status": "PASS",
          "message": null
        }
      ],
      "status": "OK",
      "message": null
    },
    {
      "test": "/wai-aria/treegrid_orientation_vertical-manual.html",
      "subtests": [
        {
          "name": "treegrid orientation vertical",
          "status": "PASS",
          "message": null
        }
      ],
      "status": "OK",
      "message": null
    },
    {
      "test": "/wai-aria/treegrid_rowcount_3-manual.html",
      "subtests": [
        {
          "name": "treegrid rowcount 3",
          "status": "PASS",
          "message": null
        }
      ],
      "status": "OK",
      "message": null
    },
    {
      "test": "/wai-aria/treeitem_selected_false-manual.html",
      "subtests": [],
      "status": "NOTRUN",
      "message": "No steps for AT API IAccessible2"
    },
    {
      "test": "/wai-aria/treeitem_selected_true-manual.html",
      "subtests": [],
      "status": "NOTRUN",
      "message": "No steps for AT API IAccessible2"
    },
    {
      "test": "/wai-aria/treeitem_selected_undefined-manual.html",
      "subtests": [],
      "status": "NOTRUN",
      "message": "No steps for AT API IAccessible2"
    },
    {
      "test": "/wai-aria/treeitem_selected_value_changes-manual.html",
      "subtests": [],
      "status": "NOTRUN",
      "message": "No steps for AT API IAccessible2"
    }
  ]
}
